resdata/__init__.py
resdata/bin.py
resdata/rd_type.py
resdata/rd_util.py
resdata/version.py
resdata/.include/ert/geometry/geo_pointset.hpp
resdata/.include/ert/geometry/geo_polygon.hpp
resdata/.include/ert/geometry/geo_polygon_collection.hpp
resdata/.include/ert/geometry/geo_region.hpp
resdata/.include/ert/geometry/geo_surface.hpp
resdata/.include/ert/geometry/geo_util.hpp
resdata/.include/ert/util/bool_vector.hpp
resdata/.include/ert/util/build_config.hpp
resdata/.include/ert/util/double_vector.hpp
resdata/.include/ert/util/ert_api_config.hpp
resdata/.include/ert/util/ert_unique_ptr.hpp
resdata/.include/ert/util/float_vector.hpp
resdata/.include/ert/util/hash.hpp
resdata/.include/ert/util/hash_node.hpp
resdata/.include/ert/util/hash_sll.hpp
resdata/.include/ert/util/int_vector.hpp
resdata/.include/ert/util/long_vector.hpp
resdata/.include/ert/util/lookup_table.hpp
resdata/.include/ert/util/mzran.hpp
resdata/.include/ert/util/node_ctype.hpp
resdata/.include/ert/util/node_data.hpp
resdata/.include/ert/util/parser.hpp
resdata/.include/ert/util/path_stack.hpp
resdata/.include/ert/util/perm_vector.hpp
resdata/.include/ert/util/rd_version.hpp
resdata/.include/ert/util/rng.hpp
resdata/.include/ert/util/size_t_vector.hpp
resdata/.include/ert/util/string_util.hpp
resdata/.include/ert/util/stringlist.hpp
resdata/.include/ert/util/test_util.hpp
resdata/.include/ert/util/test_work_area.hpp
resdata/.include/ert/util/time_t_vector.hpp
resdata/.include/ert/util/type_macros.hpp
resdata/.include/ert/util/type_vector_functions.hpp
resdata/.include/ert/util/util.hpp
resdata/.include/ert/util/util_unlink.hpp
resdata/.include/ert/util/vector.hpp
resdata/.include/resdata/FortIO.hpp
resdata/.include/resdata/ResdataKW.hpp
resdata/.include/resdata/fault_block.hpp
resdata/.include/resdata/fault_block_layer.hpp
resdata/.include/resdata/layer.hpp
resdata/.include/resdata/nnc_info.hpp
resdata/.include/resdata/nnc_vector.hpp
resdata/.include/resdata/rd_box.hpp
resdata-6.2.4.dist-info/licenses/COPYING
resdata-6.2.4.dist-info/licenses/LICENSE
resdata-6.2.4.dist-info/METADATA
resdata-6.2.4.dist-info/WHEEL
resdata-6.2.4.dist-info/top_level.txt
resdata-6.2.4.dist-info/RECORD
