Metadata-Version: 2.4
Name: resdata
Version: 6.2.4
Summary: Package for reading and writing the fortran result files from reservoir simulators
Home-page: https://github.com/equinor/resdata
Author: Equinor ASA
Author-email: fg_sib-scout@equinor.com
License: GPL-3.0
Platform: any
Classifier: Development Status :: 5 - Production/Stable
Classifier: Environment :: Other Environment
Classifier: Intended Audience :: Developers
Classifier: Intended Audience :: Science/Research
Classifier: License :: OSI Approved :: GNU General Public License v3 (GPLv3)
Classifier: Natural Language :: English
Classifier: Programming Language :: Python
Classifier: Programming Language :: Python :: 3.11
Classifier: Programming Language :: Python :: 3.12
Classifier: Programming Language :: Python :: 3.13
Classifier: Programming Language :: Python :: 3.14
Classifier: Topic :: Scientific/Engineering
Classifier: Topic :: Scientific/Engineering :: Physics
Classifier: Topic :: Software Development :: Libraries
Classifier: Topic :: Utilities
License-File: LICENSE
License-File: COPYING
Requires-Dist: cwrap
Requires-Dist: numpy
Requires-Dist: pandas
Requires-Dist: natsort
Requires-Dist: resfo-utilities>=0.4.0
Dynamic: author
Dynamic: author-email
Dynamic: classifier
Dynamic: description
Dynamic: description-content-type
Dynamic: home-page
Dynamic: license
Dynamic: license-file
Dynamic: platform
Dynamic: requires-dist
Dynamic: summary
